[
    {
        "name": "John Doe",
        "school": "xyz School",
        "category": "Senior",
        "country": "Indonesia",
        "scaledFinalScore": 98,
        "viewProposal": "https://example.com/proposal1",
        "videoPitch": "https://example.com/video19"
    },
    {
        "name": "Jane Smith",
        "school": "xyz School",
        "category": "Senior",
        "country": "Bangladesh",
        "scaledFinalScore": 96,
        "viewProposal": "https://example.com/proposal2",
        "videoPitch": "https://example.com/video19"
    },
    {
        "name": "Alice Brown",
        "school": "xyz School",
        "category": "Senior",
        "country": "Bangladesh",
        "scaledFinalScore": 94,
        "viewProposal": "https://example.com/proposal3",
        "videoPitch": "https://example.com/video19"
    },
    {
        "name": "David Black",
        "school": "xyz School university and college",
        "category": "Junior",
        "country": "Bangladesh",
        "scaledFinalScore": 89,
        "viewProposal": "https://example.com/proposal4",
        "videoPitch": "https://example.com/video19"
    },
    {
        "name": "Grace Green",
        "school": "xyz School university and college",
        "category": "Junior",
        "country": "Bangladesh",
        "scaledFinalScore": 85,
        "viewProposal": "https://example.com/proposal5",
        "videoPitch": "https://example.com/video19"
    },

  {
        "name": "John Doe",
      "school": "xyz School university and college",
        "category": "Senior",
      "country": "Bangladesh",
        "scaledFinalScore": 58,
        "viewProposal": "https://example.com/proposal1",
        "videoPitch": "https://example.com/video19"
    },
    {
        "name": "Jane Smith",
        "school": "xyz School university and college",
        "category": "Senior",
        "country": "Bangladesh",
        "scaledFinalScore": 56,
        "viewProposal": "https://example.com/proposal2",
        "videoPitch": "https://example.com/video19"
    },
    {
        "name": "Alice Brown",
        "school": "xyz School university and college",
        "category": "Senior",
        "country": "Bangladesh",
        "scaledFinalScore": 54,
        "viewProposal": "https://example.com/proposal3",
        "videoPitch": "https://example.com/video19"
    },
    {
        "name": "David Black",
        "school": "xyz School university and college",
        "category": "Junior",
        "country": "Bangladesh",
        "scaledFinalScore": 59,
        "viewProposal": "https://example.com/proposal4",
        "videoPitch": "https://example.com/video19"
    },
    {
        "name": "Grace Green",
        "school": "xyz School university and college",
        "category": "Junior",
        "country": "Bangladesh",
        "scaledFinalScore": 55,
        "viewProposal": "https://example.com/proposal5",
        "videoPitch": "https://example.com/video19"
    },

  {
        "name": "John Doe",
      "school": "xyz School university and college",
        "category": "Senior",
      "country": "Bangladesh",
        "scaledFinalScore": 58,
        "viewProposal": "https://example.com/proposal1",
        "videoPitch": "https://example.com/video19"
    },
    {
        "name": "Jane Smith",
        "school": "xyz School university and college",
        "category": "Senior",
        "country": "Bangladesh",
        "scaledFinalScore": 56,
        "viewProposal": "https://example.com/proposal2",
        "videoPitch": "https://example.com/video19"
    },
    {
        "name": "Alice Brown",
        "school": "xyz School university and college",
        "category": "Senior",
        "country": "Bangladesh",
        "scaledFinalScore": 54,
        "viewProposal": "https://example.com/proposal3",
        "videoPitch": "https://example.com/video19"
    },
    {
        "name": "David Black",
        "school": "xyz School university and college",
        "category": "Junior",
        "country": "Indonesia",
        "scaledFinalScore": 59,
        "viewProposal": "https://example.com/proposal4",
        "videoPitch": "https://example.com/video19"
    },
    {
        "name": "Grace Green",
        "school": "xyz School university and college",
        "category": "Junior",
        "country": "Bangladesh",
        "scaledFinalScore": 55,
        "viewProposal": "https://example.com/proposal5",
        "videoPitch": "https://example.com/video19"
    },

  {
        "name": "John Doe",
      "school": "xyz School university and college",
        "category": "Senior",
      "country": "Bangladesh",
        "scaledFinalScore": 48,
        "viewProposal": "https://example.com/proposal1",
        "videoPitch": "https://example.com/video19"
    },
    {
        "name": "Jane Smith",
        "school": "xyz School university and college",
        "category": "Senior",
        "country": "Bangladesh",
        "scaledFinalScore": 46,
        "viewProposal": "https://example.com/proposal2",
        "videoPitch": "https://example.com/video19"
    },
    {
        "name": "Alice Brown",
        "school": "xyz School university and college",
        "category": "Senior",
        "country": "Bangladesh",
        "scaledFinalScore": 44,
        "viewProposal": "https://example.com/proposal3",
        "videoPitch": "https://example.com/video19"
    },
    {
        "name": "David Black",
        "school": "xyz School university and college",
        "category": "Junior",
        "country": "Bangladesh",
        "scaledFinalScore": 49,
        "viewProposal": "https://example.com/proposal4",
        "videoPitch": "https://example.com/video19"
    },
    {
        "name": "Grace Green",
        "school": "xyz School university and college",
        "category": "Junior",
        "country": "Bangladesh",
        "scaledFinalScore": 45,
        "viewProposal": "https://example.com/proposal5",
        "videoPitch": "https://example.com/video19"
    },

  {
        "name": "John Doe",
      "school": "xyz School university and college",
        "category": "Senior",
      "country": "Bangladesh",
        "scaledFinalScore": 38,
        "viewProposal": "https://example.com/proposal1",
        "videoPitch": "https://example.com/video19"
    },
    {
        "name": "Jane Smith",
        "school": "xyz School university and college",
        "category": "Senior",
        "country": "Bangladesh",
        "scaledFinalScore": 36,
        "viewProposal": "https://example.com/proposal2",
        "videoPitch": "https://example.com/video19"
    },
    {
        "name": "Alice Brown",
        "school": "xyz School university and college",
        "category": "Senior",
        "country": "Bangladesh",
        "scaledFinalScore": 34,
        "viewProposal": "https://example.com/proposal3",
        "videoPitch": "https://example.com/video19"
    },
    {
        "name": "David Black",
        "school": "xyz School university and college",
        "category": "Junior",
        "country": "Bangladesh",
        "scaledFinalScore": 39,
        "viewProposal": "https://example.com/proposal4",
        "videoPitch": "https://example.com/video19"
    },
    {
        "name": "Grace Green",
        "school": "xyz School university and college",
        "category": "Junior",
        "country": "Bangladesh",
        "scaledFinalScore": 35,
        "viewProposal": "https://example.com/proposal5",
        "videoPitch": "https://example.com/video19"
    },
    {
        "name": "David Black",
        "school": "xyz School university and college",
        "category": "Junior",
        "country": "Bangladesh",
        "scaledFinalScore": 38,
        "viewProposal": "https://example.com/proposal4",
        "videoPitch": "https://example.com/video19"
    },
    {
        "name": "David Black",
        "school": "xyz School university and college",
        "category": "Junior",
        "country": "Bangladesh",
        "scaledFinalScore": 29,
        "viewProposal": "https://example.com/proposal4",
        "videoPitch": "https://example.com/video19"
    },
    {
        "name": "David Black",
        "school": "xyz School university and college",
        "category": "Junior",
        "country": "Bangladesh",
        "scaledFinalScore": 19,
        "viewProposal": "https://example.com/proposal4",
        "videoPitch": "https://example.com/video19"
    },
    {
        "name": "David Black",
        "school": "xyz School university and college",
        "category": "Junior",
        "country": "Bangladesh",
        "scaledFinalScore": 29,
        "viewProposal": "https://example.com/proposal4",
        "videoPitch": "https://example.com/video19"
    },
    {
        "name": "David Black",
        "school": "xyz School university and college",
        "category": "Junior",
        "country": "Bangladesh",
        "scaledFinalScore": 39,
        "viewProposal": "https://example.com/proposal4",
        "videoPitch": "https://example.com/video19"
    },
    {
        "name": "David Black",
        "school": "xyz School university and college",
        "category": "Junior",
        "country": "Indonesia",
        "scaledFinalScore": 39,
        "viewProposal": "https://example.com/proposal4",
        "videoPitch": "https://example.com/video19"
    }
]
